pydavinci/__init__.py
pydavinci/connect.py
pydavinci/exceptions.py
pydavinci/logger.py
pydavinci/main.py
pydavinci/py.typed
pydavinci/pyremoteobject.py
pydavinci/utils.py
pydavinci/wrappers/__init__.py
pydavinci/wrappers/_basewrappers.py
pydavinci/wrappers/_resolve_stubs.pyi
pydavinci/wrappers/folder.py
pydavinci/wrappers/gallery.py
pydavinci/wrappers/gallerystill.py
pydavinci/wrappers/gallerystillalbum.py
pydavinci/wrappers/marker.py
pydavinci/wrappers/mediapool.py
pydavinci/wrappers/mediapoolitem.py
pydavinci/wrappers/mediastorage.py
pydavinci/wrappers/project.py
pydavinci/wrappers/projectmanager.py
pydavinci/wrappers/resolve.py
pydavinci/wrappers/timeline.py
pydavinci/wrappers/timelineitem.py
pydavinci/wrappers/settings/__init__.py
pydavinci/wrappers/settings/components.py
pydavinci/wrappers/settings/constructor.py
pydavinci/wrappers/settings/map.py
pydavinci/wrappers/settings/validator.py
pydavinci_18-0.3.1.dist-info/METADATA
pydavinci_18-0.3.1.dist-info/WHEEL
pydavinci_18-0.3.1.dist-info/licenses/LICENSE
pydavinci_18-0.3.1.dist-info/RECORD
