Metadata-Version: 2.1
Name: pydavinci-18
Version: 0.3.1
Summary: Fork of PyDavinci supporting Resolve 18
Project-URL: Homepage, https://github.com/in03/pydavinci
Project-URL: Source, https://github.com/in03/pydavinci
Project-URL: Documentation, https://in03.github.io/pydavinci/resolve
Project-URL: Changelog, https://github.com/in03/pydavinci/tags
Author-email: Caleb Trevatt <sk188okj@duck.com>
License-File: LICENSE
Classifier: License :: OSI Approved :: MIT License
Classifier: Operating System :: OS Independent
Classifier: Programming Language :: Python :: 3
Requires-Python: <4.0.0,>=3.10.0
Requires-Dist: loguru>=0.6.0
Requires-Dist: pydantic>=1.9.0
Requires-Dist: typing-extensions>=4.1.1
Provides-Extra: dev
Requires-Dist: black; extra == 'dev'
Requires-Dist: mypy; extra == 'dev'
Requires-Dist: pre-commit; extra == 'dev'
Requires-Dist: pytest; extra == 'dev'
Requires-Dist: ruff; extra == 'dev'
Provides-Extra: docs
Requires-Dist: mkdocs; extra == 'docs'
Requires-Dist: mkdocs-autorefs; extra == 'docs'
Requires-Dist: mkdocs-material-extensions; extra == 'docs'
Requires-Dist: mkdocstrings; extra == 'docs'
Requires-Dist: mkdocstrings-python; extra == 'docs'
Requires-Dist: pydavinci[dev]; extra == 'docs'
